AUTHORS
LICENSE
MANIFEST.in
README.rst
THANKS
ez_setup.py
setup.py
MongoLite.egg-info/PKG-INFO
MongoLite.egg-info/SOURCES.txt
MongoLite.egg-info/dependency_links.txt
MongoLite.egg-info/not-zip-safe
MongoLite.egg-info/requires.txt
MongoLite.egg-info/top_level.txt
mongolite/__init__.py
mongolite/collection.py
mongolite/connection.py
mongolite/cursor.py
mongolite/database.py
mongolite/document.py
mongolite/helpers.py
mongolite/master_slave_connection.py
mongolite/mongo_exceptions.py
mongolite/schema_document.py
tests/test_api.py
tests/test_api.pyc
tests/test_descriptors.py
tests/test_descriptors.pyc
tests/test_gridfs.py
tests/test_gridfs.pyc
tests/test_helpers.py
tests/test_helpers.pyc
tests/test_index.py
tests/test_index.pyc
tests/test_inheritance.py
tests/test_inheritance.pyc
tests/test_inherited_queries.py
tests/test_inherited_queries.pyc
tests/test_json.py
tests/test_json.pyc
tests/test_serialize.py
tests/test_serialize.pyc
tests/test_structure.py
tests/test_structure.pyc
tests/test_types.py
tests/test_types.pyc