Metadata-Version: 1.0
Name: MongoLite
Version: 1.4
Summary: Python MongoDB light toolkit
Home-page: http://namlook.github.com/mongolite/
Author: Namlook
Author-email: UNKNOWN
License: New BSD License
Platform: UNKNOWN
Classifier: Development Status :: 5 - Production/Stable
Classifier: Environment :: Other Environment
Classifier: Intended Audience :: Developers
Classifier: License :: OSI Approved :: Apache Software License
Classifier: Operating System :: OS Independent
Classifier: Programming Language :: Python
Classifier: Topic :: Database
Classifier: Topic :: Utilities
Classifier: Topic :: Software Development :: Libraries :: Python Modules
